{
  "config": {
    "step": {
      "user": {
        "title": "cTrader App Credentials",
        "description": "Before continuing, make sure your cTrader app (https://openapi.ctrader.com) has this exact redirect URI registered:\n\n`{redirect_uri}`\n\nOnce that's set, enter your app credentials below.",
        "data": {
          "client_id": "Client ID",
          "client_secret": "Client Secret",
          "account_id": "Account ID (your cTID account number)"
        }
      },
      "auth": {
        "title": "Authorize Your cTrader Account",
        "description": "Click **Open cTrader** to log in with your cTID and allow access. You'll be redirected back to Home Assistant automatically."
      }
    },
    "error": {
      "invalid_auth": "Authentication failed. Check your credentials.",
      "unknown": "Unexpected error. Check HA logs."
    },
    "abort": {
      "already_configured": "This cTrader account is already configured.",
      "missing_code": "No authorization code received. Try again.",
      "token_exchange_failed": "Failed to exchange authorization code for tokens. Make sure the redirect URI in your cTrader app matches exactly.",
      "invalid_auth": "Tokens are invalid. Check your credentials and try again."
    }
  }
}
